chaibot/__init__.py
chaibot-0.0.1.dist-info/licenses/LICENSE
chaibot-0.0.1.dist-info/METADATA
chaibot-0.0.1.dist-info/WHEEL
chaibot-0.0.1.dist-info/top_level.txt
chaibot-0.0.1.dist-info/RECORD
