Metadata-Version: 2.4
Name: chaibot
Version: 0.0.1
Summary: CLI chatbot using Copilot or a local LLM
Author-email: Francis Peck <frncspeck@gmail.com>
License-File: LICENSE
Requires-Dist: openai>=0.27.0
Requires-Dist: llama-cpp-python>=0.1.77
Dynamic: license-file
